producer.py
raven_sdk-0.1.3.dist-info/METADATA
raven_sdk-0.1.3.dist-info/WHEEL
raven_sdk-0.1.3.dist-info/top_level.txt
raven_sdk-0.1.3.dist-info/RECORD
