Metadata-Version: 2.4
Name: raven-sdk
Version: 0.1.3
Summary: Async Kafka and HTTP producer SDK for Raven AI logs
Author-email: Ivan Kazimirau <ivan.g.kazimirov@gmail.com>
Keywords: kafka,logging,ai,async,producer
Requires-Python: >=3.8
Requires-Dist: aiokafka>=0.8
Requires-Dist: pydantic>=2.0
Requires-Dist: aiohttp>=3.8
